miden_sdk/__init__.py
miden_sdk/client.py
miden_sdk/config.py
miden_sdk/note.py
miden_sdk/transaction.py
miden_sdk/utils.py
miden_sdk/wallet.py
miden_sdk/wasm/README.md
miden_sdk-0.1.1.dist-info/licenses/LICENSE
miden_sdk-0.1.1.dist-info/METADATA
miden_sdk-0.1.1.dist-info/WHEEL
miden_sdk-0.1.1.dist-info/top_level.txt
miden_sdk-0.1.1.dist-info/RECORD
