Metadata-Version: 2.4
Name: miden-sdk
Version: 0.1.1
Summary: Python SDK for Miden blockchain
Home-page: https://github.com/chumbacash/miden-sdk
Author: Miden Python SDK Team
Author-email: amon@chumba.shop
Project-URL: Bug Tracker, https://github.com/chumbacash/miden-sdk/issues
Classifier: Programming Language :: Python :: 3
Classifier: License :: OSI Approved :: MIT License
Classifier: Operating System :: OS Independent
Classifier: Development Status :: 3 - Alpha
Requires-Python: >=3.8
License-File: LICENSE
Requires-Dist: pydantic>=2.0.0
Requires-Dist: wasmtime>=0.32.0
Requires-Dist: grpcio>=1.32.0
Requires-Dist: requests>=2.25.0
Requires-Dist: blake3>=0.3.0
Dynamic: author
Dynamic: author-email
Dynamic: classifier
Dynamic: description
Dynamic: description-content-type
Dynamic: home-page
Dynamic: license-file
Dynamic: project-url
Dynamic: requires-dist
Dynamic: requires-python
Dynamic: summary
